<root><APPLICATION ID="{3A9EFD68-0BE6-4657-B61E-32F06099DA82}" TYPENAME="ITTD" NAME="Справочник" STATUSID="" SECURITYSTYLEID="" IsLocked="2" WorkOffline="-1"><ITTD_MOROZ_COL IsLocked="0"/><ITTD_RULE_COL IsLocked="0"><ITTD_RULE ID="{62ACC0AE-030E-428C-8CF2-345526AA17C7}" Deleted="0" IsLocked="0" RetriveTime="39762.4267476852" ChangeTime="0" SECURITYSTYLEID="" NAME="Фрегат" USEPRODUCT="-1" THECOUNTRY="0" THEFACTORY="0" KILLPLACE="0" USEBRAK="-1" USEEXPDATE="0" USEPARTIA="0" AccessTime="39762.4277476852"/><ITTD_RULE ID="{D8E7EA4E-3C85-426B-AB49-36FD22D43002}" Deleted="0" IsLocked="0" RetriveTime="39762.4267476852" ChangeTime="0" SECURITYSTYLEID="" NAME="Оптимизация" USEPRODUCT="-1" THECOUNTRY="-1" THEFACTORY="-1" KILLPLACE="-1" USEBRAK="-1" USEEXPDATE="-1" USEPARTIA="0" AccessTime="39762.4277476852"/><ITTD_RULE ID="{2C598CB6-5B8A-4AF4-8009-3C399C5696C5}" Deleted="0" IsLocked="0" RetriveTime="39762.4267476852" ChangeTime="0" SECURITYSTYLEID="" NAME="МГ-Логистик" USEPRODUCT="-1" THECOUNTRY="-1" THEFACTORY="0" KILLPLACE="0" USEBRAK="-1" USEEXPDATE="0" USEPARTIA="0" AccessTime="39762.4277476852"/><ITTD_RULE ID="{ADC1B26C-B81D-427E-943F-4DE996B336BC}" Deleted="0" IsLocked="0" RetriveTime="39762.4267476852" ChangeTime="0" SECURITYSTYLEID="" NAME="Партия" USEPRODUCT="-1" THECOUNTRY="0" THEFACTORY="0" KILLPLACE="0" USEBRAK="0" USEEXPDATE="0" USEPARTIA="-1" AccessTime="39762.4277476852"/><ITTD_RULE ID="{52E5E1D4-AD8D-438D-ACE9-9BB436802270}" Deleted="0" IsLocked="0" RetriveTime="39762.4267476852" ChangeTime="0" SECURITYSTYLEID="" NAME="Мясотрейдинг" USEPRODUCT="-1" THECOUNTRY="0" THEFACTORY="0" KILLPLACE="0" USEBRAK="-1" USEEXPDATE="0" USEPARTIA="0" AccessTime="39762.4277476852"/><ITTD_RULE ID="{DED14E27-3C2F-4ADB-BCA9-A4EE5E28C884}" Deleted="0" IsLocked="0" RetriveTime="39762.4267476852" ChangeTime="0" SECURITYSTYLEID="" NAME="Рубеж" USEPRODUCT="-1" THECOUNTRY="0" THEFACTORY="0" KILLPLACE="0" USEBRAK="0" USEEXPDATE="0" USEPARTIA="0" AccessTime="39762.4277476852"/><ITTD_RULE ID="{B84318FB-DC7E-417B-B1A1-B000AAB16B55}" Deleted="0" IsLocked="0" RetriveTime="39762.4267476852" ChangeTime="0" SECURITYSTYLEID="" NAME="Дельта река" USEPRODUCT="-1" THECOUNTRY="-1" THEFACTORY="-1" KILLPLACE="-1" USEBRAK="-1" USEEXPDATE="0" USEPARTIA="0" AccessTime="39762.4277476852"/><ITTD_RULE ID="{205BB349-AAA5-4056-BED7-B56A6F238ED0}" Deleted="0" IsLocked="0" RetriveTime="39762.4267476852" ChangeTime="0" SECURITYSTYLEID="" NAME="МираТорг" USEPRODUCT="-1" THECOUNTRY="0" THEFACTORY="0" KILLPLACE="0" USEBRAK="-1" USEEXPDATE="0" USEPARTIA="0" AccessTime="39762.4277476852"/><ITTD_RULE ID="{2D1B402F-71AF-4973-B0BD-C0305B46D754}" Deleted="0" IsLocked="0" RetriveTime="39762.4267476852" ChangeTime="0" SECURITYSTYLEID="" NAME="Строгое" USEPRODUCT="-1" THECOUNTRY="-1" THEFACTORY="-1" KILLPLACE="-1" USEBRAK="-1" USEEXPDATE="0" USEPARTIA="0" AccessTime="39762.4277476852"/><ITTD_RULE ID="{AE930F11-D28E-490E-B307-C7F27139BBA5}" Deleted="0" IsLocked="0" RetriveTime="39762.4267476852" ChangeTime="0" SECURITYSTYLEID="" NAME="Итера" USEPRODUCT="-1" THECOUNTRY="-1" THEFACTORY="0" KILLPLACE="0" USEBRAK="0" USEEXPDATE="0" USEPARTIA="0" AccessTime="39762.4277476852"/><ITTD_RULE ID="{3642C501-388F-41A6-BB2C-E0AA9C0950D2}" Deleted="0" IsLocked="0" RetriveTime="39762.4267476852" ChangeTime="0" SECURITYSTYLEID="" NAME="КонтрольКодаИБрака" USEPRODUCT="-1" THECOUNTRY="0" THEFACTORY="0" KILLPLACE="0" USEBRAK="-1" USEEXPDATE="0" USEPARTIA="0" AccessTime="39762.4277476852"/><ITTD_RULE ID="{761B599B-49ED-42FA-87AC-E4F21FA05370}" Deleted="0" IsLocked="0" RetriveTime="39762.4267476852" ChangeTime="0" SECURITYSTYLEID="" NAME="рабочее" USEPRODUCT="-1" THECOUNTRY="-1" THEFACTORY="-1" KILLPLACE="0" USEBRAK="-1" USEEXPDATE="0" USEPARTIA="0" AccessTime="39762.4277476852"/><ITTD_RULE ID="{F9B855DE-B93B-43B4-AA6A-E5ACEA0C1B8E}" Deleted="0" IsLocked="0" RetriveTime="39762.4267476852" ChangeTime="0" SECURITYSTYLEID="" NAME="Карат" USEPRODUCT="-1" THECOUNTRY="0" THEFACTORY="0" KILLPLACE="0" USEBRAK="-1" USEEXPDATE="0" USEPARTIA="0" AccessTime="39762.4277476852"/><ITTD_RULE ID="{08AD3B0A-790F-4CDC-8EF2-EFAD5FA71458}" Deleted="0" IsLocked="0" RetriveTime="39762.4267476852" ChangeTime="0" SECURITYSTYLEID="" NAME="Стандартное" USEPRODUCT="-1" THECOUNTRY="-1" THEFACTORY="-1" KILLPLACE="0" USEBRAK="0" USEEXPDATE="0" USEPARTIA="0" AccessTime="39762.4277476852"/></ITTD_RULE_COL><ITTD_PLTYPE_COL IsLocked="0"><ITTD_PLTYPE ID="{8141A993-B192-47FE-9EB4-12F8ECE08745}" Deleted="0" IsLocked="0" RetriveTime="39762.4267476852" ChangeTime="0" SECURITYSTYLEID="" NAME="Индустриальная" THECODE="1" AccessTime="39762.4277476852"/><ITTD_PLTYPE ID="{C606C48F-E7AF-42A5-91E2-17A04B21262B}" Deleted="0" IsLocked="0" RetriveTime="39762.4267476852" ChangeTime="0" SECURITYSTYLEID="" NAME="euro" THECODE="0" AccessTime="39762.4277476852"/></ITTD_PLTYPE_COL><ITTD_FACTORY_COL IsLocked="0"/><ITTD_ZTYPE_COL IsLocked="0"/><ITTD_GTYPE_COL IsLocked="0"/><ITTD_KILLPLACE_COL IsLocked="0"/><ITTD_COUNTRY_COL IsLocked="0"/><ITTD_QTYPE_COL IsLocked="0"/><ITTD_CAMERA_COL IsLocked="0"><ITTD_CAMERA ID="{65A6583E-BC6C-4888-BA12-3AA63626F620}" Deleted="0" IsLocked="0" RetriveTime="39762.4267476852" ChangeTime="0" SECURITYSTYLEID="" NAME="Все камеры" CAMERAMASK="%" AccessTime="39762.4277476852"/></ITTD_CAMERA_COL><ITTD_SRV_COL IsLocked="0"><ITTD_SRV ID="{0D6A9534-9189-4FD8-A8F0-06B7CB175C6C}" Deleted="0" IsLocked="0" RetriveTime="39762.4267476852" ChangeTime="0" SECURITYSTYLEID="" NAME="Надбавка за сортировку груза по наименованиям при разгрузке, за уч. ед.(ед. сортировки) и за 1 артикул (кол-во артикулов, шт)" FORSHIPPING="0" FORRECEIVING="-1" LINKCODE="000003535" AUTOSETPALLET="0" AccessTime="39762.4277476852"/><ITTD_SRV ID="{45B2DD84-939D-4929-A0A2-06CBDBBA568A}" Deleted="0" IsLocked="0" RetriveTime="39762.4267476852" ChangeTime="0" SECURITYSTYLEID="" NAME="Ввод товарной позиции в электронную учетную систему Хранителя, за 1 позицию" FORSHIPPING="0" FORRECEIVING="-1" LINKCODE="000003496" AUTOSETPALLET="0" AccessTime="39762.4277476852"/><ITTD_SRV ID="{2ECC7E5F-7A45-4D09-966D-25523255A03F}" Deleted="0" IsLocked="0" RetriveTime="39762.4267476852" ChangeTime="0" SECURITYSTYLEID="" NAME="Перепаллетизация, за 1 паллету" FORSHIPPING="-1" FORRECEIVING="-1" LINKCODE="000003532" AUTOSETPALLET="0" AccessTime="39762.4277476852"/><ITTD_SRV ID="{A75150B0-6D75-4966-9A57-27B619F723DE}" Deleted="0" IsLocked="0" RetriveTime="39762.4267476852" ChangeTime="0" SECURITYSTYLEID="" NAME="Обмотка паллеты стрейч- пленкой, за паллету" FORSHIPPING="0" FORRECEIVING="-1" LINKCODE="000003533" AUTOSETPALLET="0" AccessTime="39762.4277476852"/><ITTD_SRV ID="{36B749D0-F6E9-4119-B4D4-2F104EF36DA7}" Deleted="0" IsLocked="0" RetriveTime="39762.4267476852" ChangeTime="0" SECURITYSTYLEID="" NAME="Погрузка груза на паллетах, за 1 паллету, за 1 операцию" FORSHIPPING="-1" FORRECEIVING="0" LINKCODE="000003493" AUTOSETPALLET="0" AccessTime="39762.4277476852"/><ITTD_SRV ID="{6222A1E0-7D7A-48CD-946D-33FE67E9F4F1}" Deleted="0" IsLocked="0" RetriveTime="39762.4267476852" ChangeTime="0" SECURITYSTYLEID="" NAME="Отгрузка груза (кг) Ежедневно с 18.00 до 9.00, а также в сб и вс" FORSHIPPING="0" FORRECEIVING="0" LINKCODE="000003488" AUTOSETPALLET="0" AccessTime="39762.4277476852"/><ITTD_SRV ID="{E890F32F-97E7-4472-9B00-45ABEF0FC8B7}" Deleted="0" IsLocked="0" RetriveTime="39762.4267476852" ChangeTime="0" SECURITYSTYLEID="" NAME="Надбавка за сбор заказа при количестве наименований в заказе более 5, но менее 10, за 1 заказ" FORSHIPPING="-1" FORRECEIVING="0" LINKCODE="000003534" AUTOSETPALLET="0" AccessTime="39762.4277476852"/><ITTD_SRV ID="{AF681B4F-4B50-44E7-AE2D-581AAAF22273}" Deleted="0" IsLocked="0" RetriveTime="39762.4267476852" ChangeTime="0" SECURITYSTYLEID="" NAME="Разгрузка груза, поступающего навалом (кг) Брутто" FORSHIPPING="0" FORRECEIVING="-1" LINKCODE="000003485" AUTOSETPALLET="0" AccessTime="39762.4277476852"/><ITTD_SRV ID="{914148F2-4012-4E41-B2E1-5978A35BAA7C}" Deleted="0" IsLocked="0" RetriveTime="39762.4267476852" ChangeTime="0" SECURITYSTYLEID="" NAME="Принято на паллетах Поклажедателя" FORSHIPPING="0" FORRECEIVING="-1" LINKCODE="000003498" AUTOSETPALLET="0" AccessTime="39762.4277476852"/><ITTD_SRV ID="{92F50F10-3C40-40EB-B0B4-63F7D89B10A6}" Deleted="0" IsLocked="0" RetriveTime="39762.4267476852" ChangeTime="0" SECURITYSTYLEID="" NAME="Отмена/корректировка Поклажедателем заявки после 21.00 часа даты подачи, за 1 заявку" FORSHIPPING="-1" FORRECEIVING="-1" LINKCODE="000003490" AUTOSETPALLET="0" AccessTime="39762.4277476852"/><ITTD_SRV ID="{373BA4BD-B223-47F9-A93C-6BBBB72F87A6}" Deleted="0" IsLocked="0" RetriveTime="39762.4267476852" ChangeTime="0" SECURITYSTYLEID="" NAME="Отгрузка груза (кг) Ежедневно с 9.00 до 18.00, кроме сб и вс" FORSHIPPING="0" FORRECEIVING="0" LINKCODE="000003487" AUTOSETPALLET="0" AccessTime="39762.4277476852"/><ITTD_SRV ID="{D24D1DB7-DC64-4A27-BEF9-7B64C03EEA59}" Deleted="0" IsLocked="0" RetriveTime="39762.4267476852" ChangeTime="0" SECURITYSTYLEID="" NAME="Упаковка груза (восстановление нарушенной заводской упаковки) за учетную единицу (или минимальную единицу груза) материалами Поклажедателя" FORSHIPPING="-1" FORRECEIVING="-1" LINKCODE="000003495" AUTOSETPALLET="0" AccessTime="39762.4277476852"/><ITTD_SRV ID="{AF806486-C441-4D59-A3CA-9780DF58A33C}" Deleted="0" IsLocked="0" RetriveTime="39762.4267476852" ChangeTime="0" SECURITYSTYLEID="" NAME="Разгрузка груза на паллетах, за 1 паллету, за 1 операцию" FORSHIPPING="0" FORRECEIVING="-1" LINKCODE="000003536" AUTOSETPALLET="0" AccessTime="39762.4277476852"/><ITTD_SRV ID="{6774D77D-6402-46F4-AE26-9D4F4F10D173}" Deleted="0" IsLocked="0" RetriveTime="39762.4267476852" ChangeTime="0" SECURITYSTYLEID="" NAME="Сортировка груза (кг) по артикулам" FORSHIPPING="0" FORRECEIVING="0" LINKCODE="000003486" AUTOSETPALLET="0" AccessTime="39762.4277476852"/><ITTD_SRV ID="{07A77422-CD86-4C11-A892-A6464EEB156A}" Deleted="0" IsLocked="0" RetriveTime="39762.4267476852" ChangeTime="0" SECURITYSTYLEID="" NAME="Хранение груза на 1 условном паллетоместе, в сутки" FORSHIPPING="0" FORRECEIVING="0" LINKCODE="" AUTOSETPALLET="0" AccessTime="39762.4277476852"/><ITTD_SRV ID="{1184BBEF-AD9C-4F98-A945-B9D308EB4B3D}" Deleted="0" IsLocked="0" RetriveTime="39762.4267476852" ChangeTime="0" SECURITYSTYLEID="" NAME="Приемка бракованного груза (бой) (кг) Брутто" FORSHIPPING="0" FORRECEIVING="-1" LINKCODE="000003492" AUTOSETPALLET="0" AccessTime="39762.4277476852"/><ITTD_SRV ID="{D35F8562-FDD5-4E50-A1E8-BEA286F3D334}" Deleted="0" IsLocked="0" RetriveTime="39762.4267476852" ChangeTime="0" SECURITYSTYLEID="" NAME="Упаковка груза (восстановление нарушенной заводской упаковки) за учетную единицу (или минимальную единицу груза) материалами Хранителя" FORSHIPPING="-1" FORRECEIVING="-1" LINKCODE="000003491" AUTOSETPALLET="0" AccessTime="39762.4277476852"/><ITTD_SRV ID="{3D478F10-8994-4195-9CC9-E628628F1D61}" Deleted="0" IsLocked="0" RetriveTime="39762.4267476852" ChangeTime="0" SECURITYSTYLEID="" NAME="Ввод заявки Поклажедателя в электронную учетную систему Хранителя, за 1 заявку " FORSHIPPING="-1" FORRECEIVING="-1" LINKCODE="000003489" AUTOSETPALLET="0" AccessTime="39762.4277476852"/><ITTD_SRV ID="{3A10CFE0-30B0-4476-8E8C-E7871D7693FD}" Deleted="0" IsLocked="0" RetriveTime="39762.4267476852" ChangeTime="0" SECURITYSTYLEID="" NAME="Отгружено паллет ООО &quot;Интертерминал - Предпортовый&quot;" FORSHIPPING="-1" FORRECEIVING="0" LINKCODE="000003497" AUTOSETPALLET="0" AccessTime="39762.4277476852"/><ITTD_SRV ID="{EE037AD6-21A4-4174-9DB5-F2360F60BD56}" Deleted="0" IsLocked="0" RetriveTime="39762.4267476852" ChangeTime="0" SECURITYSTYLEID="" NAME="Погрузка груза навалом (кг) Брутто" FORSHIPPING="-1" FORRECEIVING="0" LINKCODE="000003494" AUTOSETPALLET="0" AccessTime="39762.4277476852"/></ITTD_SRV_COL><ITTD_ATYPE_COL IsLocked="0"/><ITTD_OPTTYPE_COL IsLocked="0"><ITTD_OPTTYPE ID="{4FB26E98-7601-4F47-87C5-1EA878D8A60D}" Deleted="0" IsLocked="0" RetriveTime="39762.4267476852" ChangeTime="0" SECURITYSTYLEID="" NAME="Партия товара" CODE="6" AccessTime="39762.4277476852"/><ITTD_OPTTYPE ID="{EBB11349-9580-4286-B177-505EF809902C}" Deleted="0" IsLocked="0" RetriveTime="39762.4267476852" ChangeTime="0" SECURITYSTYLEID="" NAME="Поклажедатель - весь склад" CODE="4" AccessTime="39762.4277476852"/><ITTD_OPTTYPE ID="{34A3AEB9-B88C-4F5F-86E8-97CD77D30779}" Deleted="0" IsLocked="0" RetriveTime="39762.4267476852" ChangeTime="0" SECURITYSTYLEID="" NAME="Все камеры" CODE="0" AccessTime="39762.4277476852"/><ITTD_OPTTYPE ID="{05C39B91-4EF5-4EAC-8B0F-99A59C37066A}" Deleted="0" IsLocked="0" RetriveTime="39762.4267476852" ChangeTime="0" SECURITYSTYLEID="" NAME="Одна камера" CODE="2" AccessTime="39762.4277476852"/><ITTD_OPTTYPE ID="{01516C37-E1B9-460D-83A9-A205993DF811}" Deleted="0" IsLocked="0" RetriveTime="39762.4267476852" ChangeTime="0" SECURITYSTYLEID="" NAME="Поклажедатель - камера" CODE="5" AccessTime="39762.4277476852"/><ITTD_OPTTYPE ID="{71FE0277-420D-4214-A394-B067533AE1BF}" Deleted="0" IsLocked="0" RetriveTime="39762.4267476852" ChangeTime="0" SECURITYSTYLEID="" NAME="Склад" CODE="1" AccessTime="39762.4277476852"/><ITTD_OPTTYPE ID="{508629C5-F289-4020-A25B-E9938B6DFF44}" Deleted="0" IsLocked="0" RetriveTime="39762.4267476852" ChangeTime="0" SECURITYSTYLEID="" NAME="Один артикул" CODE="3" AccessTime="39762.4277476852"/></ITTD_OPTTYPE_COL><ITTD_EMAIL_COL IsLocked="0"/><ITTD_PART_COL IsLocked="0"/></APPLICATION></root>
